youtube_channel_transcript_api/__init__.py
youtube_channel_transcript_api/test.py
youtube_channel_transcript_api/transcripts.py
youtube_channel_transcript_api/test/__init__.py
youtube_channel_transcript_api/test/helpers.py
youtube_channel_transcript_api/test/test_api.py
youtube_channel_transcript_api-0.0.1.dist-info/LICENSE
youtube_channel_transcript_api-0.0.1.dist-info/METADATA
youtube_channel_transcript_api-0.0.1.dist-info/WHEEL
youtube_channel_transcript_api-0.0.1.dist-info/top_level.txt
youtube_channel_transcript_api-0.0.1.dist-info/RECORD
