Metadata-Version: 2.1
Name: youtube-channel-transcript-api
Version: 0.0.1
Summary: A python package the utilizes the Youtube Data V3 API to get all transcripts from a given channel/playlist.
Home-page: https://github.com/danielcliu/youtube-channel-transcript-api
Author: Daniel Liu
Author-email: dcliu@ucdavis.edu
License: UNKNOWN
Platform: UNKNOWN
Classifier: Programming Language :: Python :: 3
Classifier: License :: OSI Approved :: MIT License
Classifier: Operating System :: OS Independent
Requires-Python: >=3.6
Requires-Dist: requests
Requires-Dist: google-api-python-client
Requires-Dist: youtube-transcript-api
